xontrib/mod.py
xontrib_mod-0.1.0.dist-info/LICENSE
xontrib_mod-0.1.0.dist-info/WHEEL
xontrib_mod-0.1.0.dist-info/METADATA
xontrib_mod-0.1.0.dist-info/RECORD
