Metadata-Version: 2.1
Name: xontrib-mod
Version: 0.1.0
Summary: Lazily access modules without importing them first.
License: MIT
Author: Angus Hollands
Author-email: goosey15@gmail.com
Requires-Python: >=3.6,<4.0
Classifier: License :: OSI Approved :: MIT License
Classifier: Programming Language :: Python :: 3
Classifier: Programming Language :: Python :: 3.10
Classifier: Programming Language :: Python :: 3.6
Classifier: Programming Language :: Python :: 3.7
Classifier: Programming Language :: Python :: 3.8
Classifier: Programming Language :: Python :: 3.9
